odoo/addons/sale_financial_risk/README.rst
odoo/addons/sale_financial_risk/__init__.py
odoo/addons/sale_financial_risk/__manifest__.py
odoo/addons/sale_financial_risk/hooks.py
odoo/addons/sale_financial_risk/i18n/am.po
odoo/addons/sale_financial_risk/i18n/ar.po
odoo/addons/sale_financial_risk/i18n/bg.po
odoo/addons/sale_financial_risk/i18n/bs.po
odoo/addons/sale_financial_risk/i18n/ca.po
odoo/addons/sale_financial_risk/i18n/cs.po
odoo/addons/sale_financial_risk/i18n/da.po
odoo/addons/sale_financial_risk/i18n/de.po
odoo/addons/sale_financial_risk/i18n/el_GR.po
odoo/addons/sale_financial_risk/i18n/en_GB.po
odoo/addons/sale_financial_risk/i18n/es.po
odoo/addons/sale_financial_risk/i18n/es_CR.po
odoo/addons/sale_financial_risk/i18n/es_EC.po
odoo/addons/sale_financial_risk/i18n/es_ES.po
odoo/addons/sale_financial_risk/i18n/es_MX.po
odoo/addons/sale_financial_risk/i18n/es_VE.po
odoo/addons/sale_financial_risk/i18n/et.po
odoo/addons/sale_financial_risk/i18n/eu.po
odoo/addons/sale_financial_risk/i18n/fi.po
odoo/addons/sale_financial_risk/i18n/fr.po
odoo/addons/sale_financial_risk/i18n/fr_CA.po
odoo/addons/sale_financial_risk/i18n/fr_CH.po
odoo/addons/sale_financial_risk/i18n/gl.po
odoo/addons/sale_financial_risk/i18n/hr.po
odoo/addons/sale_financial_risk/i18n/hr_HR.po
odoo/addons/sale_financial_risk/i18n/hu.po
odoo/addons/sale_financial_risk/i18n/it.po
odoo/addons/sale_financial_risk/i18n/ja.po
odoo/addons/sale_financial_risk/i18n/lt.po
odoo/addons/sale_financial_risk/i18n/lv.po
odoo/addons/sale_financial_risk/i18n/mk.po
odoo/addons/sale_financial_risk/i18n/mn.po
odoo/addons/sale_financial_risk/i18n/nb.po
odoo/addons/sale_financial_risk/i18n/nb_NO.po
odoo/addons/sale_financial_risk/i18n/nl.po
odoo/addons/sale_financial_risk/i18n/nl_BE.po
odoo/addons/sale_financial_risk/i18n/pl.po
odoo/addons/sale_financial_risk/i18n/pt.po
odoo/addons/sale_financial_risk/i18n/pt_BR.po
odoo/addons/sale_financial_risk/i18n/pt_PT.po
odoo/addons/sale_financial_risk/i18n/ro.po
odoo_addon_sale_financial_risk-18.0.1.0.6.dist-info/METADATA
odoo_addon_sale_financial_risk-18.0.1.0.6.dist-info/WHEEL
odoo_addon_sale_financial_risk-18.0.1.0.6.dist-info/top_level.txt
odoo_addon_sale_financial_risk-18.0.1.0.6.dist-info/RECORD
