Metadata-Version: 2.1
Name: odoo-addon-sale_financial_risk
Version: 18.0.1.0.6
Requires-Python: >=3.10
Requires-Dist: odoo-addon-account_financial_risk==18.0.*
Requires-Dist: odoo==18.0.*
Summary: Manage partner risk in sales orders
Home-page: https://github.com/OCA/credit-control
License: AGPL-3
Author: Tecnativa, Odoo Community Association (OCA)
Author-email: support@odoo-community.org
Classifier: Programming Language :: Python
Classifier: Framework :: Odoo
Classifier: Framework :: Odoo :: 18.0
Classifier: License :: OSI Approved :: GNU Affero General Public License v3
